[{"item":{"value":"Q110643855","label":"The Waterloo Directory of English Newspapers and Periodicals: 1800-1900, Series Three","description":"online bibliography"},"amount":6},{"item":{"value":"P2163","label":"FAST ID","description":"authority control identifier in WorldCat's “FAST Linked Data” authority file"},"amount":6},{"item":{"value":"Q3045873","label":"JMdict","description":"multilingual Japanese–English dictionary"},"amount":4},{"item":{"value":"P1937","label":"UN/LOCODE","description":"geographic location code mantained by UNECE"},"amount":5},{"item":{"value":"P8665","label":"Présence Compositrices work ID","description":"identifier of a work on the website Présence Compositrices"},"amount":4},{"item":{"value":"P7919","label":"SerialStation game ID","description":"identifier of a video game in the SerialStation database"},"amount":7},{"item":{"value":"Q55349661","label":"Elektroniczny słownik języka polskiego XVII i XVIII wieku","description":"electronic dictionary of the Polish language of the 17th and 18th centuries"},"amount":13},{"item":{"value":"P1014","label":"Art & Architecture Thesaurus ID","description":"identifier in the Art & Architecture Thesaurus by the Getty Research Institute"},"amount":4},{"item":{"value":"P2816","label":"HowLongToBeat ID","description":"identifier of a video game at the website HowLongToBeat"},"amount":4},{"item":{"value":"P2427","label":"GRID ID","description":"institutional identifier from the GRID.ac global research identifier database"},"amount":4},{"item":{"value":"P8351","label":"vglist video game ID","description":"identifier for a video game on vglist"},"amount":4},{"item":{"value":"P6736","label":"Drobné památky ID","description":"identifier in the database of small-scale public artwork in the Czech Republic"},"amount":4},{"item":{"value":"P8116","label":"Encyclopedia of Brno History person ID","description":"identifier for people related to the city of Brno and its history"},"amount":5},{"item":{"value":"P6597","label":"Digital Dictionary of Surnames in Germany ID","description":"ID of corresponding entry in the DFD online dictionary of family names"},"amount":5},{"item":{"value":"P6337","label":"PCGamingWiki ID","description":"identifier for PC video games tracked on PCGamingWiki"},"amount":5},{"item":{"value":"P6238","label":"Monument aux morts ID","description":"identifier for a memorial in the University of Lille database"},"amount":4},{"item":{"value":"P5737","label":"Moegirlpedia ID","description":"Chinese-, Japanese-, or English-language articles and categories about ACG culture hosted on any of the Moegirlpedia family of wikis"},"amount":5},{"item":{"value":"P6228","label":"RegiowikiAT ID","description":"numeric identifier of a page in the Austria regional wiki RegiowikiAT"},"amount":5},{"item":{"value":"P7597","label":"Lutris game ID","description":"identifier of a video game in the Lutris database"},"amount":4},{"item":{"value":"P8523","label":"Présence Compositrices composer ID","description":"identifier of a female composer on the website Présence Compositrices"},"amount":5},{"item":{"value":"P3206","label":"data.gouv.fr organisation ID","description":"identifier of an organization on the French national open-data platform data.gouv.fr"},"amount":4},{"item":{"value":"P5868","label":"MobyGames platform ID","description":"identifier for a platform in MobyGames"},"amount":6},{"item":{"value":"P5247","label":"Giant Bomb ID","description":"identifier at the Giant Bomb database of video games, fictional characters and voice actors"},"amount":5},{"item":{"value":"P6853","label":"Coco Game List ID","description":"identifier in the Coco Game List of Color Computer video games"},"amount":6},{"item":{"value":"P6554","label":"Represent Me ID","description":"identifier of games on Represent Me"},"amount":4},{"item":{"value":"Q328","label":"English Wikipedia","description":"English-language edition of Wikipedia"},"amount":8},{"item":{"value":"P908","label":"PEGI rating","description":"European video game content rating system"},"amount":4},{"item":{"value":"P6760","label":"Know Your Meme ID","description":"identifier for a Know Your Meme article"},"amount":4},{"item":{"value":"P6782","label":"ROR ID","description":"identifier for the Research Organization Registry"},"amount":4},{"item":{"value":"P5269","label":"Web umenia work ID","description":"identifier for an artwork or other object on the Web umenia website"},"amount":4},{"item":{"value":"P1933","label":"MobyGames game ID","description":"identifier for MobyGames"},"amount":9},{"item":{"value":"P6844","label":"abART person ID","description":"identifier of person in the Czech database abART"},"amount":5},{"item":{"value":"P5796","label":"Internet Game Database person ID","description":"identifier for a person on the Internet Game Database"},"amount":4},{"item":{"value":"P5794","label":"Internet Game Database game ID","description":"identifier for a game on the Internet Game Database"},"amount":7},{"item":{"value":"P9067","label":"Hungarian Film Archive ID","description":"identifier of a movie in the database of the Hungarian Film Archive"},"amount":4},{"item":{"value":"P8752","label":"Kramerius of Moravian Library UUID","description":"UUID identifier for scanned item (book edition/periodical/page) in Moravian Library"},"amount":4},{"item":{"value":"P5421","label":"Trading Card Database person ID","description":"identifier for a person or fictional character in the Trading Card Database (TCDb)"},"amount":5},{"item":{"value":"P497","label":"CBDB ID","description":"identifer for a person in the China Biographical Database"},"amount":4},{"item":{"value":"P2481","label":"Elite Prospects player ID","description":"ice hockey player ID assigned by Elite Prospects"},"amount":5},{"item":{"value":"P4965","label":"Behind The Voice Actors video game ID","description":"identifier for video games on the website Behind The Voice Actors"},"amount":12},{"item":{"value":"P5652","label":"Carthalia ID","description":"ID of a page at \"Carthalia - Theatres on Postcards\""},"amount":4},{"item":{"value":"P7902","label":"Deutsche Biographie (GND) ID","description":"GND identifier for an item in the Deutsche Biographie"},"amount":11},{"item":{"value":"P227","label":"GND ID","description":"identifier from an international authority file of names, subjects, and organizations (please don't use type n = name, disambiguation) - Deutsche Nationalbibliothek"},"amount":7},{"item":{"value":"P7859","label":"WorldCat Identities ID","description":"entity on WorldCat. Use P243 OCLC control number for books"},"amount":5},{"item":{"value":"P496","label":"ORCID iD","description":"identifier for a person"},"amount":5},{"item":{"value":"P402","label":"OpenStreetMap relation ID","description":"identifier for a relation in OpenStreetMap"},"amount":6},{"item":{"value":"P8804","label":"stolpersteine-hamburg.de Stolperstein identifier","description":"identifier for Stolpersteine in Hamburg issued by stolpersteine-hamburg.de"},"amount":5},{"item":{"value":"P356","label":"DOI","description":"serial code used to uniquely identify digital objects like academic papers (use upper case letters only)"},"amount":10},{"item":{"value":"P5659","label":"VGMdb product ID","description":"identifier for a product (game, franchise, video) in the Video Game Music database"},"amount":4}]